dragonfly/__init__.py
dragonfly/dragonfly.py
dragonfly/examples.py
dragonfly/util.py
tests/__init__.py
tests/test_dragonfly.py
dragonfly_sync_lib-1.0.0.dist-info/LICENSE
dragonfly_sync_lib-1.0.0.dist-info/METADATA
dragonfly_sync_lib-1.0.0.dist-info/WHEEL
dragonfly_sync_lib-1.0.0.dist-info/top_level.txt
dragonfly_sync_lib-1.0.0.dist-info/RECORD
